aws_codebuild/__init__.py
aws_codebuild/_version.py
aws_codebuild/arg.py
aws_codebuild/arn_and_console.py
aws_codebuild/better_boto.py
aws_codebuild/compat.py
aws_codebuild/env_var.py
aws_codebuild/notification.py
aws_codebuild/tests/__init__.py
aws_codebuild/tests/boto_ses.py
aws_codebuild/tests/helper.py
aws_codebuild/tests/paths.py
aws_codebuild-1.2.1.dist-info/AUTHORS.rst
aws_codebuild-1.2.1.dist-info/LICENSE.txt
aws_codebuild-1.2.1.dist-info/METADATA
aws_codebuild-1.2.1.dist-info/WHEEL
aws_codebuild-1.2.1.dist-info/top_level.txt
aws_codebuild-1.2.1.dist-info/RECORD
